BAC0/__init__.py
BAC0/infos.py
BAC0/core/__init__.py
BAC0/core/app/__init__.py
BAC0/core/app/asyncApp.py
BAC0/core/app/device.json
BAC0/core/devices/Device.py
BAC0/core/devices/Points.py
BAC0/core/devices/Trends.py
BAC0/core/devices/Virtuals.py
BAC0/core/devices/__init__.py
BAC0/core/devices/local/__init__.py
BAC0/core/devices/local/decorator.py
BAC0/core/devices/local/factory.py
BAC0/core/devices/local/object.py
BAC0/core/devices/local/trendLogs.py
BAC0/core/devices/mixins/__init__.py
BAC0/core/devices/mixins/read_mixin.py
BAC0/core/functions/Alias.py
BAC0/core/functions/Calendar.py
BAC0/core/functions/CoV.py
BAC0/core/functions/Discover.py
BAC0/core/functions/EventEnrollment.py
BAC0/core/functions/GetIPAddr.py
BAC0/core/functions/Reinitialize.py
BAC0/core/functions/Schedule.py
BAC0/core/functions/Text.py
BAC0/core/functions/TimeSync.py
BAC0/core/functions/__init__.py
BAC0/core/io/IOExceptions.py
BAC0/core/io/Read.py
BAC0/core/io/Simulate.py
BAC0/core/io/Write.py
BAC0/core/io/__init__.py
BAC0/core/proprietary_objects/__init__.py
BAC0/core/proprietary_objects/jci_5.py
BAC0/core/proprietary_objects/privablue_105.py
BAC0/core/proprietary_objects/produal_783.py
BAC0/core/utils/__init__.py
BAC0/core/utils/lookfordependency.py
BAC0/core/utils/notes.py
BAC0/db/__init__.py
BAC0/db/influxdb.py
BAC0/db/sql.py
BAC0/scripts/Base.py
BAC0/scripts/Lite.py
BAC0/scripts/__init__.py
BAC0/scripts/script_runner.py
BAC0/tasks/Devices.py
BAC0/tasks/DoOnce.py
BAC0/tasks/Match.py
BAC0/tasks/Poll.py
BAC0/tasks/RecurringTask.py
BAC0/tasks/TaskManager.py
BAC0/tasks/__init__.py
BAC0/tools/__init__.py
BAC0/tools/const.py
BAC0/tools/jci_tec_points_list.py
BAC0/tools/tad_display.py
bac0-2025.8.9.dist-info/licenses/LICENSE
bac0-2025.8.9.dist-info/METADATA
bac0-2025.8.9.dist-info/WHEEL
bac0-2025.8.9.dist-info/top_level.txt
bac0-2025.8.9.dist-info/RECORD
