Metadata-Version: 2.4
Name: BAC0
Version: 2025.8.9
Summary: BACnet Scripting Framework for testing DDC Controls
Author-email: Christian Tremblay <christian.tremblay@servisys.com>
License: LGPL-3.0
Project-URL: Homepage, https://github.com/ChristianTremblay/BAC0
Keywords: bacnet,building,automation,test
License-File: LICENSE
Requires-Dist: BACpypes3
Requires-Dist: colorama
Requires-Dist: python-dotenv
Requires-Dist: pytz
Requires-Dist: aiosqlite
Provides-Extra: extras
Requires-Dist: pandas; extra == "extras"
Requires-Dist: influxdb_client[async]; extra == "extras"
Requires-Dist: aiohttp; extra == "extras"
Requires-Dist: rich; extra == "extras"
Requires-Dist: pytest-asyncio; extra == "extras"
Requires-Dist: coverage; extra == "extras"
Dynamic: license-file
